<databaseChangeLog xmlns="http://www.liquibase.org/xml/ns/dbchangelog"
    xmlns:ext="http://www.liquibase.org/xml/ns/dbchangelog-ext"
    xmlns:xsi="http://www.w3.org/2001/XMLSchema-instance"
    xmlns:pro="http://www.liquibase.org/xml/ns/pro"
    xsi:schemaLocation="http://www.liquibase.org/xml/ns/dbchangelog-ext http://www.liquibase.org/xml/ns/dbchangelog/dbchangelog-ext.xsd
http://www.liquibase.org/xml/ns/dbchangelog http://www.liquibase.org/xml/ns/dbchangelog/dbchangelog-3.5.xsd
  http://www.liquibase.org/xml/ns/pro http://www.liquibase.org/xml/ns/pro/liquibase-pro-3.8.xsd">

  <changeSet author="aaron" id="1::createTableBook">
    <createTable tableName="BOOK" schemaName="book_store">
      <column name="ID" type="BIGINT" autoIncrement="true">
        <constraints primaryKey="true" nullable="false"/>
      </column>
      <column name="TITLE" type="VARCHAR"/>
      <column name="PRICE" type="NUMERIC"/>
    </createTable>
  </changeSet>

  <changeSet author="aaron" id="2::populateBook">
    <insert tableName="BOOK" schemaName="book_store">
      <column name="TITLE" value="A Storm of Swords"/>
      <column name="PRICE" value="20"/>
    </insert>
    <insert tableName="BOOK" schemaName="book_store">
      <column name="TITLE" value="A Feast for Crows"/>
      <column name="PRICE" value="25"/>
    </insert>
  </changeSet>

</databaseChangeLog>